mcp_manager/__init__.py
mcp_manager/cli/__init__.py
mcp_manager/cli/main.py
mcp_manager/core/__init__.py
mcp_manager/core/server.py
mcp_manager/core/server_manager.py
mcp_manager/models/__init__.py
mcp_manager/models/server.py
mcp_manager/server/__init__.py
mcp_manager/server/auth.py
mcp_manager/server/globals.py
mcp_manager/server/logging.py
mcp_manager/server/main.py
mcp_manager/server/routes/__init__.py
mcp_manager/server/routes/server_sse.py
mcp_manager/server/routes/servers.py
mcp_manager/server/routes/sse.py
mcp_manager/server/routes/tools.py
mcp_manager/utils/__init__.py
mcp_manager/utils/loader.py
mcp_manager_cli-1.0.1.dist-info/licenses/LICENSE
mcp_manager_cli-1.0.1.dist-info/METADATA
mcp_manager_cli-1.0.1.dist-info/WHEEL
mcp_manager_cli-1.0.1.dist-info/entry_points.txt
mcp_manager_cli-1.0.1.dist-info/top_level.txt
mcp_manager_cli-1.0.1.dist-info/RECORD
