Metadata-Version: 2.4
Name: mcp-manager-cli
Version: 1.0.1
Summary: A unified CLI and daemon/service to manage and proxy multiple MCP servers, with robust logging and a modern CLI UX.
Author-email: Khai Trinh Xuan <khai.trinh@cloudthinker.io>
License-Expression: MIT
Keywords: cli,mcp,manager
Requires-Python: >=3.10
License-File: LICENSE
Requires-Dist: fastapi<1.0.0,>=0.115.12
Requires-Dist: fastmcp>=2.5.2
Requires-Dist: prompt-toolkit>=3.0.51
Requires-Dist: pydantic>=2.11.5
Requires-Dist: pytest>=8.3.5
Requires-Dist: rich>=14.0.0
Dynamic: license-file
